ros_rosidl_runtime_cpp-4.9.5.data/data/include/rosidl_runtime_cpp/rosidl_runtime_cpp/action_type_support_decl.hpp
ros_rosidl_runtime_cpp-4.9.5.data/data/include/rosidl_runtime_cpp/rosidl_runtime_cpp/bounded_vector.hpp
ros_rosidl_runtime_cpp-4.9.5.data/data/include/rosidl_runtime_cpp/rosidl_runtime_cpp/message_initialization.hpp
ros_rosidl_runtime_cpp-4.9.5.data/data/include/rosidl_runtime_cpp/rosidl_runtime_cpp/message_type_support_decl.hpp
ros_rosidl_runtime_cpp-4.9.5.data/data/include/rosidl_runtime_cpp/rosidl_runtime_cpp/service_type_support_decl.hpp
ros_rosidl_runtime_cpp-4.9.5.data/data/include/rosidl_runtime_cpp/rosidl_runtime_cpp/traits.hpp
ros_rosidl_runtime_cpp-4.9.5.data/data/include/rosidl_runtime_cpp/rosidl_runtime_cpp/type_description/field__struct.hpp
ros_rosidl_runtime_cpp-4.9.5.data/data/include/rosidl_runtime_cpp/rosidl_runtime_cpp/type_description/field_type__struct.hpp
ros_rosidl_runtime_cpp-4.9.5.data/data/include/rosidl_runtime_cpp/rosidl_runtime_cpp/type_description/individual_type_description__struct.hpp
ros_rosidl_runtime_cpp-4.9.5.data/data/include/rosidl_runtime_cpp/rosidl_runtime_cpp/type_description/key_value__struct.hpp
ros_rosidl_runtime_cpp-4.9.5.data/data/include/rosidl_runtime_cpp/rosidl_runtime_cpp/type_description/type_description__struct.hpp
ros_rosidl_runtime_cpp-4.9.5.data/data/include/rosidl_runtime_cpp/rosidl_runtime_cpp/type_description/type_source__struct.hpp
ros_rosidl_runtime_cpp-4.9.5.data/data/include/rosidl_runtime_cpp/rosidl_typesupport_cpp/action_type_support.hpp
ros_rosidl_runtime_cpp-4.9.5.data/data/include/rosidl_runtime_cpp/rosidl_typesupport_cpp/message_type_support.hpp
ros_rosidl_runtime_cpp-4.9.5.data/data/include/rosidl_runtime_cpp/rosidl_typesupport_cpp/service_type_support.hpp
ros_rosidl_runtime_cpp-4.9.5.data/data/share/ament_index/resource_index/package_run_dependencies/rosidl_runtime_cpp
ros_rosidl_runtime_cpp-4.9.5.data/data/share/ament_index/resource_index/packages/rosidl_runtime_cpp
ros_rosidl_runtime_cpp-4.9.5.dist-info/METADATA
ros_rosidl_runtime_cpp-4.9.5.dist-info/WHEEL
ros_rosidl_runtime_cpp-4.9.5.dist-info/top_level.txt
ros_rosidl_runtime_cpp-4.9.5.dist-info/RECORD
