Metadata-Version: 2.4
Name: ros-rosidl-runtime-cpp
Version: 4.9.5
Summary: A ROS package that generates and provides C++ runtime interfaces for ROSIDL definitions.
Requires-Dist: ros-rosidl-runtime-c~=4.9.5
Dynamic: description
Dynamic: description-content-type
Dynamic: requires-dist
Dynamic: summary
